git_latest_tag_plugin/__init__.py
git_latest_tag_plugin/plugin.py
mkdocs_latest_release_plugin/__init__.py
mkdocs_latest_release_plugin/plugin.py
mkdocs_latest_release_plugin-0.1.2.dist-info/LICENSE
mkdocs_latest_release_plugin-0.1.2.dist-info/METADATA
mkdocs_latest_release_plugin-0.1.2.dist-info/WHEEL
mkdocs_latest_release_plugin-0.1.2.dist-info/entry_points.txt
mkdocs_latest_release_plugin-0.1.2.dist-info/top_level.txt
mkdocs_latest_release_plugin-0.1.2.dist-info/RECORD
