Metadata-Version: 2.1
Name: mkdocs-latest-release-plugin
Version: 0.1.2
Summary: MkDocs plugin to display the latest version based on git tags.
Home-page: https://github.com/agarthetiger/mkdocs_latest_release_plugin/
License: GPL v3
Platform: UNKNOWN
Classifier: Development Status :: 3 - Alpha
Classifier: Programming Language :: Python
Classifier: License :: OSI Approved :: GNU General Public License v3 (GPLv3)
Classifier: Operating System :: OS Independent
Requires-Python: >=3.4
Requires-Dist: GitPython
Requires-Dist: jinja2
Requires-Dist: mkdocs (>=0.17)
Requires-Dist: natsort
